Metadata-Version: 1.0
Name: pypi1i29
Version: 0.1
Summary: Gaussian and Binomial distributions
Home-page: UNKNOWN
Author: Mahesh Khatri
Author-email: khatrimahesh@gmail.com
License: UNKNOWN
Platform: UNKNOWN
